scrapy_kafka_export/__init__.py
scrapy_kafka_export/extensions.py
scrapy_kafka_export/utils.py
scrapy_kafka_export/writer.py
scrapy_kafka_export-0.1.1.dist-info/DESCRIPTION.rst
scrapy_kafka_export-0.1.1.dist-info/METADATA
scrapy_kafka_export-0.1.1.dist-info/RECORD
scrapy_kafka_export-0.1.1.dist-info/WHEEL
scrapy_kafka_export-0.1.1.dist-info/metadata.json
scrapy_kafka_export-0.1.1.dist-info/top_level.txt
