Metadata-Version: 2.0
Name: scrapy-kafka-export
Version: 0.1.1
Summary: Export Scrapy items to Kafka
Home-page: https://github.com/TeamHG-Memex/scrapy-kafka-export
Author: UNKNOWN
Author-email: UNKNOWN
License: MIT license
Platform: UNKNOWN
Classifier: Development Status :: 3 - Alpha
Classifier: License :: OSI Approved :: MIT License
Classifier: Intended Audience :: Developers
Classifier: Operating System :: OS Independent
Classifier: Framework :: Scrapy
Classifier: Programming Language :: Python
Classifier: Programming Language :: Python :: 2
Classifier: Programming Language :: Python :: 2.7
Classifier: Programming Language :: Python :: 3
Classifier: Programming Language :: Python :: 3.4
Classifier: Programming Language :: Python :: 3.5
Classifier: Programming Language :: Python :: 3.6
Requires-Dist: kafka-python
Requires-Dist: retrying
